pybricksmenu/__init__.py
pybricksmenu-0.0.6.dist-info/METADATA
pybricksmenu-0.0.6.dist-info/WHEEL
pybricksmenu-0.0.6.dist-info/licenses/LICENSE.md
pybricksmenu-0.0.6.dist-info/RECORD
