Metadata-Version: 2.4
Name: pybricksmenu
Version: 0.0.6
Summary: Main menu for pybricks
Project-URL: Homepage, https://github.com/joeyparrish/pybricksmenu
Project-URL: Issues, https://github.com/joeyparrish/pybricksmenu/issues
Author-email: Joey Parrish <joey.parrish@gmail.com>
License-Expression: GPL-3.0-or-later
License-File: LICENSE.md
Classifier: Operating System :: OS Independent
Classifier: Programming Language :: Python :: 3
Requires-Python: >=3.9
Requires-Dist: pybricks>=3.6.1
